Metadata-Version: 2.1
Name: shkspr
Version: 0
Summary: Uses Nginx X-Accel to provide auth for microservices
Home-page: http://github.com/theSage21/shakespeare
Author: Arjoonn Sharma
Author-email: arjoonn.94@gmail.com
License: MIT
Keywords: shkspr
Platform: UNKNOWN
